spotlight/__init__.py
spotlight/admin/__init__.py
spotlight/admin/__util.py
spotlight/admin/asynchronous.py
spotlight/admin/synchronous.py
spotlight/api/__init__.py
spotlight/api/alert/__init__.py
spotlight/api/alert/__util.py
spotlight/api/alert/asynchronous.py
spotlight/api/alert/model.py
spotlight/api/alert/synchronous.py
spotlight/api/auth/__init__.py
spotlight/api/auth/__util.py
spotlight/api/auth/asynchronous.py
spotlight/api/auth/synchronous.py
spotlight/api/data/__init__.py
spotlight/api/data/__util.py
spotlight/api/data/asynchronous.py
spotlight/api/data/model.py
spotlight/api/data/synchronous.py
spotlight/api/data/barchart/__init__.py
spotlight/api/data/barchart/__util.py
spotlight/api/data/barchart/asynchronous.py
spotlight/api/data/barchart/model.py
spotlight/api/data/barchart/synchronous.py
spotlight/api/data_rule/__init__.py
spotlight/api/data_rule/__util.py
spotlight/api/data_rule/asynchronous.py
spotlight/api/data_rule/model.py
spotlight/api/data_rule/synchronous.py
spotlight/api/dataset/__init__.py
spotlight/api/dataset/__util.py
spotlight/api/dataset/asynchronous.py
spotlight/api/dataset/model.py
spotlight/api/dataset/synchronous.py
spotlight/api/dataset/abstract/__init__.py
spotlight/api/dataset/abstract/__util.py
spotlight/api/dataset/abstract/asynchronous.py
spotlight/api/dataset/abstract/model.py
spotlight/api/dataset/abstract/synchronous.py
spotlight/api/dataset/view/__init__.py
spotlight/api/dataset/view/__util.py
spotlight/api/dataset/view/asynchronous.py
spotlight/api/dataset/view/model.py
spotlight/api/dataset/view/synchronous.py
spotlight/api/permission/__init__.py
spotlight/api/permission/__util.py
spotlight/api/permission/asynchronous.py
spotlight/api/permission/enum.py
spotlight/api/permission/model.py
spotlight/api/permission/synchronous.py
spotlight/api/sdr_source/__init__.py
spotlight/api/sdr_source/__util.py
spotlight/api/sdr_source/asynchronous.py
spotlight/api/sdr_source/synchronous.py
spotlight/core/__init__.py
spotlight_sdk-0.2.4.dist-info/METADATA
spotlight_sdk-0.2.4.dist-info/WHEEL
spotlight_sdk-0.2.4.dist-info/top_level.txt
spotlight_sdk-0.2.4.dist-info/RECORD
