Metadata-Version: 2.4
Name: spotlight-sdk
Version: 0.2.4
Summary: Spotlight Python SDK
Home-page: https://spotlight.dev
Author: Spotlight
Author-email: hello@spotlight.dev
Classifier: Programming Language :: Python :: 3
Classifier: Operating System :: OS Independent
Requires-Python: >=3.7
Requires-Dist: requests>=2.31.0
Requires-Dist: aiohttp>=3.8.4
Requires-Dist: pandas>=2.0.1
Requires-Dist: duckdb>=0.7.1
Requires-Dist: trycast>=1.0.0
Requires-Dist: pydash>=7.0.3
Requires-Dist: cachetools>=5.3.0
Requires-Dist: pydantic==1.10.17
Requires-Dist: aiocache>=0.12.1
Requires-Dist: backoff>=2.2.1
Requires-Dist: asyncstdlib>=3.10.7
Dynamic: author
Dynamic: author-email
Dynamic: classifier
Dynamic: description
Dynamic: description-content-type
Dynamic: home-page
Dynamic: requires-dist
Dynamic: requires-python
Dynamic: summary
